LICENSE
README.rst
setup.py
scav/__init__.py
scav.egg-info/PKG-INFO
scav.egg-info/SOURCES.txt
scav.egg-info/dependency_links.txt
scav.egg-info/requires.txt
scav.egg-info/top_level.txt
scav/embedding_level/__init__.py
scav/embedding_level/classifier_manager.py
scav/embedding_level/embedding_manager.py
scav/embedding_level/instructions.py
scav/embedding_level/layer_classifier.py
scav/embedding_level/llm_config.py
scav/embedding_level/model_base.py
scav/embedding_level/model_extraction.py
scav/embedding_level/model_generation.py
scav/embedding_level/perturbation.py
scav/embedding_level/plot.py
scav/embedding_level/reduction.py
scav/prompt_level/__init__.py
scav/prompt_level/cav.py
scav/prompt_level/modelwrapper.py