Metadata-Version: 2.1
Name: scav
Version: 1.2
Summary: SCAV: Safety Concept Activation Vector Jailbreak Framework
Home-page: https://github.com/SproutNan/AI-Safety_SCAV
Author: SCAV Team
Author-email: rhuangbi@connect.ust.hk
License: MIT
Platform: any
Classifier: Development Status :: 3 - Alpha
Classifier: Intended Audience :: Developers
Classifier: License :: OSI Approved :: MIT License
Classifier: Programming Language :: Python :: 3
Classifier: Programming Language :: Python :: 3.10
License-File: LICENSE
Requires-Dist: transformers
Requires-Dist: torch
Requires-Dist: numpy
